PrettyPrint/PrintGraph.py
PrettyPrint/PrintTree.py
PrettyPrint/Tests.py
PrettyPrint/__init__.py
PrettyPrint/playground.py
PrettyPrint/test.py
PrettyPrint/PrintLinkedList/LinkedListFormatter.py
PrettyPrint/PrintLinkedList/LinkedListPrinter.py
PrettyPrint/PrintLinkedList/__init__.py
PrettyPrint/PrintTree/HorizontalTree.py
PrettyPrint/PrintTree/JsonTree.py
PrettyPrint/PrintTree/TreeFormatter.py
PrettyPrint/PrintTree/TreePrinter.py
PrettyPrint/PrintTree/VerticalTree.py
PrettyPrint/PrintTree/__init__.py
PrettyPrint/Utils/NodeFormatter.py
PrettyPrint/Utils/Orientation.py
PrettyPrint/Utils/StyleAwareUtils.py
PrettyPrint/Utils/ZipLongest.py
PrettyPrint/Utils/__init__.py
PrettyPrintTree-2.0.0.dist-info/METADATA
PrettyPrintTree-2.0.0.dist-info/WHEEL
PrettyPrintTree-2.0.0.dist-info/top_level.txt
PrettyPrintTree-2.0.0.dist-info/RECORD
