Metadata-Version: 2.1
Name: PrettyPrintTree
Version: 2.0.0
Summary: A tool to print trees to the console
Home-page: https://github.com/AharonSambol/PrettyPrintTree
Author: Aharon Sambol
Author-email: email@example.com
License: MIT License
Keywords: tree,pretty,print,pretty-print,display
Requires-Dist: colorama
Requires-Dist: cmd2
